{
  "table_name": "nypd_arrests_data__historic__20231019",
  "schema": "csv_files",
  "database": "csv_files",
  "row_count": 1010745,
  "columns": [
    {
      "name": "ARREST_KEY",
      "type": "BIGINT",
      "nullable": true,
      "metadata": {
        "distinct_count": 1010745,
        "min": "9926902",
        "max": "261186607"
      }
    },
    {
      "name": "ARREST_DATE",
      "type": "DATE",
      "nullable": true,
      "metadata": {
        "distinct_count": 6209,
        "min": "2006-01-01",
        "max": "2022-12-31"
      }
    },
    {
      "name": "PD_CD",
      "type": "BIGINT",
      "nullable": true,
      "metadata": {
        "distinct_count": 168,
        "min": "0",
        "max": "997"
      }
    },
    {
      "name": "PD_DESC",
      "type": "VARCHAR",
      "nullable": true,
      "metadata": {
        "distinct_count": 186
      }
    },
    {
      "name": "KY_CD",
      "type": "VARCHAR",
      "nullable": true,
      "metadata": {
        "distinct_count": 47,
        "value_distribution": [
          {
            "value": "344",
            "count": 492902,
            "percentage": 48.77
          },
          {
            "value": "118",
            "count": 108486,
            "percentage": 10.73
          },
          {
            "value": "361",
            "count": 82993,
            "percentage": 8.21
          },
          {
            "value": "359",
            "count": 67107,
            "percentage": 6.64
          },
          {
            "value": "126",
            "count": 49855,
            "percentage": 4.93
          },
          {
            "value": "106",
            "count": 29434,
            "percentage": 2.91
          },
          {
            "value": "356",
            "count": 28242,
            "percentage": 2.79
          },
          {
            "value": "355",
            "count": 21854,
            "percentage": 2.16
          },
          {
            "value": "364",
            "count": 17019,
            "percentage": 1.68
          },
          {
            "value": "104",
            "count": 13817,
            "percentage": 1.37
          },
          {
            "value": "121",
            "count": 13599,
            "percentage": 1.35
          },
          {
            "value": "353",
            "count": 13404,
            "percentage": 1.33
          },
          {
            "value": "116",
            "count": 12450,
            "percentage": 1.23
          },
          {
            "value": null,
            "count": 9739,
            "percentage": 0.96
          },
          {
            "value": "348",
            "count": 9726,
            "percentage": 0.96
          },
          {
            "value": "346",
            "count": 6402,
            "percentage": 0.63
          },
          {
            "value": "995",
            "count": 5968,
            "percentage": 0.59
          },
          {
            "value": "880",
            "count": 5472,
            "percentage": 0.54
          },
          {
            "value": "112",
            "count": 5110,
            "percentage": 0.51
          },
          {
            "value": "117",
            "count": 3826,
            "percentage": 0.38
          },
          {
            "value": "881",
            "count": 2342,
            "percentage": 0.23
          },
          {
            "value": "235",
            "count": 1553,
            "percentage": 0.15
          },
          {
            "value": "678",
            "count": 1247,
            "percentage": 0.12
          },
          {
            "value": "124",
            "count": 1083,
            "percentage": 0.11
          },
          {
            "value": "343",
            "count": 981,
            "percentage": 0.1
          },
          {
            "value": "572",
            "count": 838,
            "percentage": 0.08
          },
          {
            "value": "351",
            "count": 778,
            "percentage": 0.08
          },
          {
            "value": "120",
            "count": 629,
            "percentage": 0.06
          },
          {
            "value": "358",
            "count": 625,
            "percentage": 0.06
          },
          {
            "value": "360",
            "count": 580,
            "percentage": 0.06
          },
          {
            "value": "230",
            "count": 491,
            "percentage": 0.05
          },
          {
            "value": "109",
            "count": 434,
            "percentage": 0.04
          },
          {
            "value": "365",
            "count": 372,
            "percentage": 0.04
          },
          {
            "value": "125",
            "count": 324,
            "percentage": 0.03
          },
          {
            "value": "237",
            "count": 299,
            "percentage": 0.03
          },
          {
            "value": "233",
            "count": 291,
            "percentage": 0.03
          },
          {
            "value": "115",
            "count": 130,
            "percentage": 0.01
          },
          {
            "value": "114",
            "count": 119,
            "percentage": 0.01
          },
          {
            "value": "340",
            "count": 89,
            "percentage": 0.01
          },
          {
            "value": "455",
            "count": 65,
            "percentage": 0.01
          },
          {
            "value": "236",
            "count": 26,
            "percentage": 0.0
          },
          {
            "value": "882",
            "count": 13,
            "percentage": 0.0
          },
          {
            "value": "357",
            "count": 12,
            "percentage": 0.0
          },
          {
            "value": "123",
            "count": 10,
            "percentage": 0.0
          },
          {
            "value": "250",
            "count": 4,
            "percentage": 0.0
          },
          {
            "value": "677",
            "count": 3,
            "percentage": 0.0
          },
          {
            "value": "672",
            "count": 1,
            "percentage": 0.0
          },
          {
            "value": " POSSESSION 7",
            "count": 1,
            "percentage": 0.0
          }
        ]
      }
    },
    {
      "name": "OFNS_DESC",
      "type": "VARCHAR",
      "nullable": true,
      "metadata": {
        "distinct_count": 55
      }
    },
    {
      "name": "LAW_CODE",
      "type": "VARCHAR",
      "nullable": true,
      "metadata": {
        "distinct_count": 870
      }
    },
    {
      "name": "LAW_CAT_CD",
      "type": "VARCHAR",
      "nullable": true,
      "metadata": {
        "distinct_count": 6,
        "value_distribution": [
          {
            "value": "M",
            "count": 748192,
            "percentage": 74.02
          },
          {
            "value": "F",
            "count": 246514,
            "percentage": 24.39
          },
          {
            "value": "I",
            "count": 6915,
            "percentage": 0.68
          },
          {
            "value": null,
            "count": 6164,
            "percentage": 0.61
          },
          {
            "value": "V",
            "count": 2503,
            "percentage": 0.25
          },
          {
            "value": "9",
            "count": 456,
            "percentage": 0.05
          },
          {
            "value": "PL 2200300",
            "count": 1,
            "percentage": 0.0
          }
        ]
      }
    },
    {
      "name": "ARREST_BORO",
      "type": "VARCHAR",
      "nullable": true,
      "metadata": {
        "distinct_count": 5,
        "value_distribution": [
          {
            "value": "K",
            "count": 286759,
            "percentage": 28.37
          },
          {
            "value": "B",
            "count": 243796,
            "percentage": 24.12
          },
          {
            "value": "Q",
            "count": 224866,
            "percentage": 22.25
          },
          {
            "value": "M",
            "count": 215273,
            "percentage": 21.3
          },
          {
            "value": "S",
            "count": 40050,
            "percentage": 3.96
          },
          {
            "value": null,
            "count": 1,
            "percentage": 0.0
          }
        ]
      }
    },
    {
      "name": "ARREST_PRECINCT",
      "type": "VARCHAR",
      "nullable": true,
      "metadata": {
        "distinct_count": 78
      }
    },
    {
      "name": "JURISDICTION_CODE",
      "type": "BIGINT",
      "nullable": true,
      "metadata": {
        "distinct_count": 28,
        "value_distribution": [
          {
            "value": 0,
            "count": 904823,
            "percentage": 89.52
          },
          {
            "value": 2,
            "count": 54593,
            "percentage": 5.4
          },
          {
            "value": 1,
            "count": 26537,
            "percentage": 2.63
          },
          {
            "value": 97,
            "count": 8918,
            "percentage": 0.88
          },
          {
            "value": 3,
            "count": 5526,
            "percentage": 0.55
          },
          {
            "value": 69,
            "count": 1895,
            "percentage": 0.19
          },
          {
            "value": 73,
            "count": 1393,
            "percentage": 0.14
          },
          {
            "value": 6,
            "count": 1156,
            "percentage": 0.11
          },
          {
            "value": 72,
            "count": 968,
            "percentage": 0.1
          },
          {
            "value": 14,
            "count": 966,
            "percentage": 0.1
          },
          {
            "value": 11,
            "count": 670,
            "percentage": 0.07
          },
          {
            "value": 71,
            "count": 630,
            "percentage": 0.06
          },
          {
            "value": 15,
            "count": 538,
            "percentage": 0.05
          },
          {
            "value": 7,
            "count": 513,
            "percentage": 0.05
          },
          {
            "value": 85,
            "count": 468,
            "percentage": 0.05
          },
          {
            "value": 4,
            "count": 378,
            "percentage": 0.04
          },
          {
            "value": 87,
            "count": 252,
            "percentage": 0.02
          },
          {
            "value": 13,
            "count": 121,
            "percentage": 0.01
          },
          {
            "value": 16,
            "count": 117,
            "percentage": 0.01
          },
          {
            "value": 9,
            "count": 87,
            "percentage": 0.01
          },
          {
            "value": 88,
            "count": 81,
            "percentage": 0.01
          },
          {
            "value": 12,
            "count": 73,
            "percentage": 0.01
          },
          {
            "value": 79,
            "count": 21,
            "percentage": 0.0
          },
          {
            "value": 74,
            "count": 7,
            "percentage": 0.0
          },
          {
            "value": 76,
            "count": 6,
            "percentage": 0.0
          },
          {
            "value": 8,
            "count": 5,
            "percentage": 0.0
          },
          {
            "value": 27,
            "count": 1,
            "percentage": 0.0
          },
          {
            "value": 82,
            "count": 1,
            "percentage": 0.0
          },
          {
            "value": null,
            "count": 1,
            "percentage": 0.0
          }
        ]
      }
    },
    {
      "name": "AGE_GROUP",
      "type": "VARCHAR",
      "nullable": true,
      "metadata": {
        "distinct_count": 35,
        "value_distribution": [
          {
            "value": "25-44",
            "count": 514976,
            "percentage": 50.95
          },
          {
            "value": "18-24",
            "count": 256712,
            "percentage": 25.4
          },
          {
            "value": "45-64",
            "count": 153351,
            "percentage": 15.17
          },
          {
            "value": "<18",
            "count": 76498,
            "percentage": 7.57
          },
          {
            "value": "65+",
            "count": 9167,
            "percentage": 0.91
          },
          {
            "value": null,
            "count": 7,
            "percentage": 0.0
          },
          {
            "value": "940",
            "count": 2,
            "percentage": 0.0
          },
          {
            "value": "922",
            "count": 2,
            "percentage": 0.0
          },
          {
            "value": "1916",
            "count": 2,
            "percentage": 0.0
          },
          {
            "value": "945",
            "count": 2,
            "percentage": 0.0
          },
          {
            "value": "UNKNOWN",
            "count": 1,
            "percentage": 0.0
          },
          {
            "value": "931",
            "count": 1,
            "percentage": 0.0
          },
          {
            "value": "317",
            "count": 1,
            "percentage": 0.0
          },
          {
            "value": "912",
            "count": 1,
            "percentage": 0.0
          },
          {
            "value": "930",
            "count": 1,
            "percentage": 0.0
          },
          {
            "value": "894",
            "count": 1,
            "percentage": 0.0
          },
          {
            "value": "1048",
            "count": 1,
            "percentage": 0.0
          },
          {
            "value": "1942",
            "count": 1,
            "percentage": 0.0
          },
          {
            "value": "1922",
            "count": 1,
            "percentage": 0.0
          },
          {
            "value": "723",
            "count": 1,
            "percentage": 0.0
          },
          {
            "value": "951",
            "count": 1,
            "percentage": 0.0
          },
          {
            "value": "194",
            "count": 1,
            "percentage": 0.0
          },
          {
            "value": "929",
            "count": 1,
            "percentage": 0.0
          },
          {
            "value": "924",
            "count": 1,
            "percentage": 0.0
          },
          {
            "value": "939",
            "count": 1,
            "percentage": 0.0
          },
          {
            "value": "926",
            "count": 1,
            "percentage": 0.0
          },
          {
            "value": "338",
            "count": 1,
            "percentage": 0.0
          },
          {
            "value": "895",
            "count": 1,
            "percentage": 0.0
          },
          {
            "value": "1",
            "count": 1,
            "percentage": 0.0
          },
          {
            "value": "914",
            "count": 1,
            "percentage": 0.0
          },
          {
            "value": "941",
            "count": 1,
            "percentage": 0.0
          },
          {
            "value": "212",
            "count": 1,
            "percentage": 0.0
          },
          {
            "value": "934",
            "count": 1,
            "percentage": 0.0
          },
          {
            "value": "927",
            "count": 1,
            "percentage": 0.0
          },
          {
            "value": "938",
            "count": 1,
            "percentage": 0.0
          },
          {
            "value": "816",
            "count": 1,
            "percentage": 0.0
          }
        ]
      }
    },
    {
      "name": "PERP_SEX",
      "type": "VARCHAR",
      "nullable": true,
      "metadata": {
        "distinct_count": 3,
        "value_distribution": [
          {
            "value": "M",
            "count": 793125,
            "percentage": 78.47
          },
          {
            "value": "F",
            "count": 217619,
            "percentage": 21.53
          },
          {
            "value": "18-24",
            "count": 1,
            "percentage": 0.0
          }
        ]
      }
    },
    {
      "name": "PERP_RACE",
      "type": "VARCHAR",
      "nullable": true,
      "metadata": {
        "distinct_count": 9,
        "value_distribution": [
          {
            "value": "BLACK",
            "count": 489549,
            "percentage": 48.43
          },
          {
            "value": "WHITE HISPANIC",
            "count": 260533,
            "percentage": 25.78
          },
          {
            "value": "WHITE",
            "count": 111589,
            "percentage": 11.04
          },
          {
            "value": "BLACK HISPANIC",
            "count": 81026,
            "percentage": 8.02
          },
          {
            "value": "ASIAN / PACIFIC ISLANDER",
            "count": 54726,
            "percentage": 5.41
          },
          {
            "value": "UNKNOWN",
            "count": 10345,
            "percentage": 1.02
          },
          {
            "value": "AMERICAN INDIAN/ALASKAN NATIVE",
            "count": 2669,
            "percentage": 0.26
          },
          {
            "value": "OTHER",
            "count": 307,
            "percentage": 0.03
          },
          {
            "value": "M",
            "count": 1,
            "percentage": 0.0
          }
        ]
      }
    },
    {
      "name": "X_COORD_CD",
      "type": "VARCHAR",
      "nullable": true,
      "metadata": {
        "distinct_count": 85227
      }
    },
    {
      "name": "Y_COORD_CD",
      "type": "DOUBLE",
      "nullable": true,
      "metadata": {
        "distinct_count": 58275,
        "min": "121131.0",
        "max": "8202360.0"
      }
    },
    {
      "name": "Latitude",
      "type": "DOUBLE",
      "nullable": true,
      "metadata": {
        "distinct_count": 95840,
        "min": "40.49890536300006",
        "max": "62.08307497800007"
      }
    },
    {
      "name": "Longitude",
      "type": "DOUBLE",
      "nullable": true,
      "metadata": {
        "distinct_count": 96099,
        "min": "-74.25474318899995",
        "max": "-73.68178026799995"
      }
    },
    {
      "name": "Lon_Lat",
      "type": "VARCHAR",
      "nullable": true,
      "metadata": {
        "distinct_count": 101064
      }
    }
  ],
  "sample_rows": [
    {
      "ARREST_KEY": 236791704,
      "ARREST_DATE": "2021-11-22 00:00:00",
      "PD_CD": 581,
      "PD_DESC": null,
      "KY_CD": null,
      "OFNS_DESC": null,
      "LAW_CODE": "PL 2225001",
      "LAW_CAT_CD": "M",
      "ARREST_BORO": "M",
      "ARREST_PRECINCT": "28",
      "JURISDICTION_CODE": 0,
      "AGE_GROUP": "45-64",
      "PERP_SEX": "M",
      "PERP_RACE": "BLACK",
      "X_COORD_CD": "997427",
      "Y_COORD_CD": 230378.0,
      "Latitude": 40.799008797000056,
      "Longitude": -73.95240854099995,
      "Lon_Lat": "POINT (-73.95240854099995 40.799008797000056)"
    },
    {
      "ARREST_KEY": 237354740,
      "ARREST_DATE": "2021-12-04 00:00:00",
      "PD_CD": 153,
      "PD_DESC": "RAPE 3",
      "KY_CD": "104",
      "OFNS_DESC": "RAPE",
      "LAW_CODE": "PL 1302502",
      "LAW_CAT_CD": "F",
      "ARREST_BORO": "B",
      "ARREST_PRECINCT": "41",
      "JURISDICTION_CODE": 0,
      "AGE_GROUP": "25-44",
      "PERP_SEX": "M",
      "PERP_RACE": "WHITE HISPANIC",
      "X_COORD_CD": "1013232",
      "Y_COORD_CD": 236725.0,
      "Latitude": 40.816391847000034,
      "Longitude": -73.89529641399997,
      "Lon_Lat": "POINT (-73.89529641399997 40.816391847000034)"
    },
    {
      "ARREST_KEY": 32311380,
      "ARREST_DATE": "2007-06-18 00:00:00",
      "PD_CD": 511,
      "PD_DESC": "CONTROLLED SUBSTANCE",
      "KY_CD": " POSSESSION 7",
      "OFNS_DESC": "235",
      "LAW_CODE": "DANGEROUS DRUGS",
      "LAW_CAT_CD": "PL 2200300",
      "ARREST_BORO": "M",
      "ARREST_PRECINCT": "Q",
      "JURISDICTION_CODE": 27,
      "AGE_GROUP": "1",
      "PERP_SEX": "18-24",
      "PERP_RACE": "M",
      "X_COORD_CD": "BLACK",
      "Y_COORD_CD": NaN,
      "Latitude": NaN,
      "Longitude": NaN,
      "Lon_Lat": null
    },
    {
      "ARREST_KEY": 192799737,
      "ARREST_DATE": "2019-01-26 00:00:00",
      "PD_CD": 177,
      "PD_DESC": "SEXUAL ABUSE",
      "KY_CD": "116",
      "OFNS_DESC": "SEX CRIMES",
      "LAW_CODE": "PL 1306503",
      "LAW_CAT_CD": "F",
      "ARREST_BORO": "M",
      "ARREST_PRECINCT": "25",
      "JURISDICTION_CODE": 0,
      "AGE_GROUP": "45-64",
      "PERP_SEX": "M",
      "PERP_RACE": "BLACK",
      "X_COORD_CD": "1000555",
      "Y_COORD_CD": 230994.0,
      "Latitude": 40.800694331000045,
      "Longitude": -73.94110928599997,
      "Lon_Lat": "POINT (-73.94110928599997 40.800694331000045)"
    },
    {
      "ARREST_KEY": 193260691,
      "ARREST_DATE": "2019-02-06 00:00:00",
      "PD_CD": null,
      "PD_DESC": null,
      "KY_CD": null,
      "OFNS_DESC": null,
      "LAW_CODE": "PL 2203400",
      "LAW_CAT_CD": "F",
      "ARREST_BORO": "M",
      "ARREST_PRECINCT": "14",
      "JURISDICTION_CODE": 0,
      "AGE_GROUP": "25-44",
      "PERP_SEX": "M",
      "PERP_RACE": "UNKNOWN",
      "X_COORD_CD": "986685",
      "Y_COORD_CD": 215375.0,
      "Latitude": 40.75783900300007,
      "Longitude": -73.99121211099998,
      "Lon_Lat": "POINT (-73.99121211099998 40.75783900300007)"
    },
    {
      "ARREST_KEY": 237291769,
      "ARREST_DATE": "2021-12-03 00:00:00",
      "PD_CD": 579,
      "PD_DESC": null,
      "KY_CD": null,
      "OFNS_DESC": null,
      "LAW_CODE": "PL 2224001",
      "LAW_CAT_CD": "F",
      "ARREST_BORO": "Q",
      "ARREST_PRECINCT": "115",
      "JURISDICTION_CODE": 0,
      "AGE_GROUP": "25-44",
      "PERP_SEX": "M",
      "PERP_RACE": "BLACK",
      "X_COORD_CD": "1018534",
      "Y_COORD_CD": 220579.0,
      "Latitude": 40.77205649600006,
      "Longitude": -73.87622400099998,
      "Lon_Lat": "POINT (-73.87622400099998 40.77205649600006)"
    },
    {
      "ARREST_KEY": 149117452,
      "ARREST_DATE": "2016-01-06 00:00:00",
      "PD_CD": 153,
      "PD_DESC": "RAPE 3",
      "KY_CD": "104",
      "OFNS_DESC": "RAPE",
      "LAW_CODE": "PL 1302503",
      "LAW_CAT_CD": "F",
      "ARREST_BORO": "K",
      "ARREST_PRECINCT": "67",
      "JURISDICTION_CODE": 0,
      "AGE_GROUP": "25-44",
      "PERP_SEX": "M",
      "PERP_RACE": "BLACK",
      "X_COORD_CD": "998032.0",
      "Y_COORD_CD": 175598.0,
      "Latitude": 40.648650085000035,
      "Longitude": -73.95033556299995,
      "Lon_Lat": "POINT (-73.95033556299995 40.648650085000035)"
    },
    {
      "ARREST_KEY": 237339209,
      "ARREST_DATE": "2021-12-04 00:00:00",
      "PD_CD": 101,
      "PD_DESC": "ASSAULT 3",
      "KY_CD": "344",
      "OFNS_DESC": "ASSAULT 3 & RELATED OFFENSES",
      "LAW_CODE": "PL 1200001",
      "LAW_CAT_CD": "M",
      "ARREST_BORO": "K",
      "ARREST_PRECINCT": "83",
      "JURISDICTION_CODE": 0,
      "AGE_GROUP": "25-44",
      "PERP_SEX": "M",
      "PERP_RACE": "BLACK",
      "X_COORD_CD": "1007400",
      "Y_COORD_CD": 190154.0,
      "Latitude": 40.688583516000044,
      "Longitude": -73.91652634699994,
      "Lon_Lat": "POINT (-73.91652634699994 40.688583516000044)"
    },
    {
      "ARREST_KEY": 221756278,
      "ARREST_DATE": "2020-12-12 00:00:00",
      "PD_CD": null,
      "PD_DESC": null,
      "KY_CD": null,
      "OFNS_DESC": null,
      "LAW_CODE": "PL 2203400",
      "LAW_CAT_CD": "F",
      "ARREST_BORO": "M",
      "ARREST_PRECINCT": "23",
      "JURISDICTION_CODE": 0,
      "AGE_GROUP": "25-44",
      "PERP_SEX": "M",
      "PERP_RACE": "WHITE HISPANIC",
      "X_COORD_CD": "999998",
      "Y_COORD_CD": 226211.0,
      "Latitude": 40.78756730100001,
      "Longitude": -73.94313233199995,
      "Lon_Lat": "POINT (-73.94313233199995 40.78756730100001)"
    },
    {
      "ARREST_KEY": 237580757,
      "ARREST_DATE": "2021-12-09 00:00:00",
      "PD_CD": 105,
      "PD_DESC": "STRANGULATION 1ST",
      "KY_CD": "106",
      "OFNS_DESC": "FELONY ASSAULT",
      "LAW_CODE": "PL 1211200",
      "LAW_CAT_CD": "F",
      "ARREST_BORO": "M",
      "ARREST_PRECINCT": "30",
      "JURISDICTION_CODE": 0,
      "AGE_GROUP": "25-44",
      "PERP_SEX": "M",
      "PERP_RACE": "BLACK",
      "X_COORD_CD": "999751",
      "Y_COORD_CD": 241188.0,
      "Latitude": 40.82867545800008,
      "Longitude": -73.94398971599996,
      "Lon_Lat": "POINT (-73.94398971599996 40.82867545800008)"
    },
    {
      "ARREST_KEY": 190049060,
      "ARREST_DATE": "2018-11-15 00:00:00",
      "PD_CD": 157,
      "PD_DESC": "RAPE 1",
      "KY_CD": "104",
      "OFNS_DESC": "RAPE",
      "LAW_CODE": "PL 1303501",
      "LAW_CAT_CD": "F",
      "ARREST_BORO": "K",
      "ARREST_PRECINCT": "77",
      "JURISDICTION_CODE": 0,
      "AGE_GROUP": "25-44",
      "PERP_SEX": "M",
      "PERP_RACE": "BLACK",
      "X_COORD_CD": "1003606",
      "Y_COORD_CD": 185050.0,
      "Latitude": 40.67458330800008,
      "Longitude": -73.93022154099998,
      "Lon_Lat": "POINT (-73.93022154099998 40.67458330800008)"
    },
    {
      "ARREST_KEY": 220422940,
      "ARREST_DATE": "2020-11-12 00:00:00",
      "PD_CD": 157,
      "PD_DESC": "RAPE 1",
      "KY_CD": "104",
      "OFNS_DESC": "RAPE",
      "LAW_CODE": "PL 1303502",
      "LAW_CAT_CD": "F",
      "ARREST_BORO": "Q",
      "ARREST_PRECINCT": "112",
      "JURISDICTION_CODE": 0,
      "AGE_GROUP": "25-44",
      "PERP_SEX": "M",
      "PERP_RACE": "BLACK",
      "X_COORD_CD": "1025420",
      "Y_COORD_CD": 202485.0,
      "Latitude": 40.72236368700004,
      "Longitude": -73.85147389399998,
      "Lon_Lat": "POINT (-73.85147389399998 40.72236368700005)"
    },
    {
      "ARREST_KEY": 189182271,
      "ARREST_DATE": "2018-10-24 00:00:00",
      "PD_CD": 153,
      "PD_DESC": "RAPE 3",
      "KY_CD": "104",
      "OFNS_DESC": "RAPE",
      "LAW_CODE": "PL 1302503",
      "LAW_CAT_CD": "F",
      "ARREST_BORO": "M",
      "ARREST_PRECINCT": "5",
      "JURISDICTION_CODE": 0,
      "AGE_GROUP": "45-64",
      "PERP_SEX": "M",
      "PERP_RACE": "WHITE HISPANIC",
      "X_COORD_CD": "984946",
      "Y_COORD_CD": 200203.0,
      "Latitude": 40.716195914000025,
      "Longitude": -73.99749074599998,
      "Lon_Lat": "POINT (-73.99749074599998 40.716195914000025)"
    },
    {
      "ARREST_KEY": 214798896,
      "ARREST_DATE": "2020-07-01 00:00:00",
      "PD_CD": 177,
      "PD_DESC": "SEXUAL ABUSE",
      "KY_CD": "116",
      "OFNS_DESC": "SEX CRIMES",
      "LAW_CODE": "PL 1306504",
      "LAW_CAT_CD": "F",
      "ARREST_BORO": "B",
      "ARREST_PRECINCT": "46",
      "JURISDICTION_CODE": 0,
      "AGE_GROUP": "25-44",
      "PERP_SEX": "M",
      "PERP_RACE": "BLACK",
      "X_COORD_CD": "1011881",
      "Y_COORD_CD": 250411.0,
      "Latitude": 40.85396027400003,
      "Longitude": -73.90012087499997,
      "Lon_Lat": "POINT (-73.90012087499997 40.85396027400004)"
    },
    {
      "ARREST_KEY": 196324211,
      "ARREST_DATE": "2019-04-23 00:00:00",
      "PD_CD": 157,
      "PD_DESC": "RAPE 1",
      "KY_CD": "104",
      "OFNS_DESC": "RAPE",
      "LAW_CODE": "PL 1303501",
      "LAW_CAT_CD": "F",
      "ARREST_BORO": "K",
      "ARREST_PRECINCT": "77",
      "JURISDICTION_CODE": 0,
      "AGE_GROUP": "45-64",
      "PERP_SEX": "M",
      "PERP_RACE": "BLACK HISPANIC",
      "X_COORD_CD": "1003606",
      "Y_COORD_CD": 185050.0,
      "Latitude": 40.67458330800008,
      "Longitude": -73.93022154099998,
      "Lon_Lat": "POINT (-73.93022154099998 40.67458330800008)"
    },
    {
      "ARREST_KEY": 189129210,
      "ARREST_DATE": "2018-10-23 00:00:00",
      "PD_CD": 101,
      "PD_DESC": "ASSAULT 3",
      "KY_CD": "344",
      "OFNS_DESC": "ASSAULT 3 & RELATED OFFENSES",
      "LAW_CODE": "PL 1200000",
      "LAW_CAT_CD": "M",
      "ARREST_BORO": "M",
      "ARREST_PRECINCT": "18",
      "JURISDICTION_CODE": 0,
      "AGE_GROUP": "25-44",
      "PERP_SEX": "M",
      "PERP_RACE": "WHITE HISPANIC",
      "X_COORD_CD": "987501",
      "Y_COORD_CD": 217778.0,
      "Latitude": 40.76443435900006,
      "Longitude": -73.988265529,
      "Lon_Lat": "POINT (-73.988265529 40.76443435900006)"
    },
    {
      "ARREST_KEY": 237856894,
      "ARREST_DATE": "2021-12-15 00:00:00",
      "PD_CD": 101,
      "PD_DESC": "ASSAULT 3",
      "KY_CD": "344",
      "OFNS_DESC": "ASSAULT 3 & RELATED OFFENSES",
      "LAW_CODE": "PL 1200001",
      "LAW_CAT_CD": "M",
      "ARREST_BORO": "B",
      "ARREST_PRECINCT": "43",
      "JURISDICTION_CODE": 0,
      "AGE_GROUP": "25-44",
      "PERP_SEX": "M",
      "PERP_RACE": "BLACK",
      "X_COORD_CD": "1021043",
      "Y_COORD_CD": 241958.0,
      "Latitude": 40.83072585600007,
      "Longitude": -73.86704848399995,
      "Lon_Lat": "POINT (-73.86704848399995 40.83072585600007)"
    },
    {
      "ARREST_KEY": 220303765,
      "ARREST_DATE": "2020-11-10 00:00:00",
      "PD_CD": 153,
      "PD_DESC": "RAPE 3",
      "KY_CD": "104",
      "OFNS_DESC": "RAPE",
      "LAW_CODE": "PL 1302501",
      "LAW_CAT_CD": "F",
      "ARREST_BORO": "Q",
      "ARREST_PRECINCT": "112",
      "JURISDICTION_CODE": 0,
      "AGE_GROUP": "25-44",
      "PERP_SEX": "M",
      "PERP_RACE": "BLACK",
      "X_COORD_CD": "1025420",
      "Y_COORD_CD": 202485.0,
      "Latitude": 40.72236368700004,
      "Longitude": -73.85147389399998,
      "Lon_Lat": "POINT (-73.85147389399998 40.72236368700005)"
    },
    {
      "ARREST_KEY": 189176315,
      "ARREST_DATE": "2018-10-24 00:00:00",
      "PD_CD": 475,
      "PD_DESC": null,
      "KY_CD": null,
      "OFNS_DESC": null,
      "LAW_CODE": "PL 1651601",
      "LAW_CAT_CD": "M",
      "ARREST_BORO": "M",
      "ARREST_PRECINCT": "28",
      "JURISDICTION_CODE": 1,
      "AGE_GROUP": "25-44",
      "PERP_SEX": "M",
      "PERP_RACE": "BLACK",
      "X_COORD_CD": "999346",
      "Y_COORD_CD": 233573.0,
      "Latitude": 40.80777512600008,
      "Longitude": -73.94547028299998,
      "Lon_Lat": "POINT (-73.94547028299998 40.80777512600008)"
    },
    {
      "ARREST_KEY": 238116432,
      "ARREST_DATE": "2021-12-21 00:00:00",
      "PD_CD": 579,
      "PD_DESC": null,
      "KY_CD": null,
      "OFNS_DESC": null,
      "LAW_CODE": "PL 2224002",
      "LAW_CAT_CD": "F",
      "ARREST_BORO": "Q",
      "ARREST_PRECINCT": "113",
      "JURISDICTION_CODE": 0,
      "AGE_GROUP": "25-44",
      "PERP_SEX": "M",
      "PERP_RACE": "WHITE HISPANIC",
      "X_COORD_CD": "1046405",
      "Y_COORD_CD": 187113.0,
      "Latitude": 40.680048726000045,
      "Longitude": -73.77590919399995,
      "Lon_Lat": "POINT (-73.77590919399995 40.680048726000045)"
    },
    {
      "ARREST_KEY": 237302061,
      "ARREST_DATE": "2021-12-03 00:00:00",
      "PD_CD": null,
      "PD_DESC": null,
      "KY_CD": null,
      "OFNS_DESC": null,
      "LAW_CODE": "PL 2203400",
      "LAW_CAT_CD": "F",
      "ARREST_BORO": "M",
      "ARREST_PRECINCT": "14",
      "JURISDICTION_CODE": 0,
      "AGE_GROUP": "25-44",
      "PERP_SEX": "M",
      "PERP_RACE": "BLACK HISPANIC",
      "X_COORD_CD": "986195",
      "Y_COORD_CD": 213562.0,
      "Latitude": 40.752862899000036,
      "Longitude": -73.99298133199994,
      "Lon_Lat": "POINT (-73.99298133199994 40.752862899000036)"
    },
    {
      "ARREST_KEY": 238376572,
      "ARREST_DATE": "2021-12-28 00:00:00",
      "PD_CD": 579,
      "PD_DESC": null,
      "KY_CD": null,
      "OFNS_DESC": null,
      "LAW_CODE": "PL 2223501",
      "LAW_CAT_CD": "F",
      "ARREST_BORO": "K",
      "ARREST_PRECINCT": "72",
      "JURISDICTION_CODE": 0,
      "AGE_GROUP": "25-44",
      "PERP_SEX": "M",
      "PERP_RACE": "ASIAN / PACIFIC ISLANDER",
      "X_COORD_CD": "981639",
      "Y_COORD_CD": 172112.0,
      "Latitude": 40.63909210100008,
      "Longitude": -74.00940929499995,
      "Lon_Lat": "POINT (-74.00940929499995 40.63909210100008)"
    },
    {
      "ARREST_KEY": 220917769,
      "ARREST_DATE": "2020-11-24 00:00:00",
      "PD_CD": 157,
      "PD_DESC": "RAPE 1",
      "KY_CD": "104",
      "OFNS_DESC": "RAPE",
      "LAW_CODE": "PL 1303501",
      "LAW_CAT_CD": "F",
      "ARREST_BORO": "B",
      "ARREST_PRECINCT": "41",
      "JURISDICTION_CODE": 0,
      "AGE_GROUP": "25-44",
      "PERP_SEX": "M",
      "PERP_RACE": "BLACK",
      "X_COORD_CD": "1013232",
      "Y_COORD_CD": 236725.0,
      "Latitude": 40.816391847000034,
      "Longitude": -73.89529641399997,
      "Lon_Lat": "POINT (-73.89529641399997 40.816391847000034)"
    },
    {
      "ARREST_KEY": 236918575,
      "ARREST_DATE": "2021-11-24 00:00:00",
      "PD_CD": 153,
      "PD_DESC": "RAPE 3",
      "KY_CD": "104",
      "OFNS_DESC": "RAPE",
      "LAW_CODE": "PL 1302502",
      "LAW_CAT_CD": "F",
      "ARREST_BORO": "Q",
      "ARREST_PRECINCT": "114",
      "JURISDICTION_CODE": 0,
      "AGE_GROUP": "25-44",
      "PERP_SEX": "M",
      "PERP_RACE": "WHITE",
      "X_COORD_CD": "1007654",
      "Y_COORD_CD": 219564.0,
      "Latitude": 40.76930608700008,
      "Longitude": -73.91550817999997,
      "Lon_Lat": "POINT (-73.91550817999997 40.76930608700008)"
    },
    {
      "ARREST_KEY": 238350561,
      "ARREST_DATE": "2021-12-28 00:00:00",
      "PD_CD": 157,
      "PD_DESC": "RAPE 1",
      "KY_CD": "104",
      "OFNS_DESC": "RAPE",
      "LAW_CODE": "PL 1303501",
      "LAW_CAT_CD": "F",
      "ARREST_BORO": "B",
      "ARREST_PRECINCT": "41",
      "JURISDICTION_CODE": 0,
      "AGE_GROUP": "25-44",
      "PERP_SEX": "M",
      "PERP_RACE": "WHITE HISPANIC",
      "X_COORD_CD": "1013232",
      "Y_COORD_CD": 236725.0,
      "Latitude": 40.816391847000034,
      "Longitude": -73.89529641399997,
      "Lon_Lat": "POINT (-73.89529641399997 40.816391847000034)"
    },
    {
      "ARREST_KEY": 199836526,
      "ARREST_DATE": "2019-07-16 00:00:00",
      "PD_CD": 105,
      "PD_DESC": "STRANGULATION 1ST",
      "KY_CD": "106",
      "OFNS_DESC": "FELONY ASSAULT",
      "LAW_CODE": "PL 1211200",
      "LAW_CAT_CD": "F",
      "ARREST_BORO": "Q",
      "ARREST_PRECINCT": "113",
      "JURISDICTION_CODE": 0,
      "AGE_GROUP": "45-64",
      "PERP_SEX": "M",
      "PERP_RACE": "BLACK",
      "X_COORD_CD": "1039470",
      "Y_COORD_CD": 185436.0,
      "Latitude": 40.67549172900004,
      "Longitude": -73.80092613699998,
      "Lon_Lat": "POINT (-73.80092613699998 40.67549172900004)"
    },
    {
      "ARREST_KEY": 236949124,
      "ARREST_DATE": "2021-11-26 00:00:00",
      "PD_CD": 105,
      "PD_DESC": "STRANGULATION 1ST",
      "KY_CD": "106",
      "OFNS_DESC": "FELONY ASSAULT",
      "LAW_CODE": "PL 1211200",
      "LAW_CAT_CD": "F",
      "ARREST_BORO": "S",
      "ARREST_PRECINCT": "121",
      "JURISDICTION_CODE": 0,
      "AGE_GROUP": "18-24",
      "PERP_SEX": "M",
      "PERP_RACE": "WHITE",
      "X_COORD_CD": "942825",
      "Y_COORD_CD": 166367.0,
      "Latitude": 40.623226819000074,
      "Longitude": -74.14922697299994,
      "Lon_Lat": "POINT (-74.14922697299994 40.623226819000074)"
    },
    {
      "ARREST_KEY": 189228258,
      "ARREST_DATE": "2018-10-26 00:00:00",
      "PD_CD": 563,
      "PD_DESC": "PROSTITUTION",
      "KY_CD": "356",
      "OFNS_DESC": "PROSTITUTION & RELATED OFFENSES",
      "LAW_CODE": "PL 2300000",
      "LAW_CAT_CD": "M",
      "ARREST_BORO": "Q",
      "ARREST_PRECINCT": "103",
      "JURISDICTION_CODE": 0,
      "AGE_GROUP": "18-24",
      "PERP_SEX": "F",
      "PERP_RACE": "WHITE",
      "X_COORD_CD": "1041717",
      "Y_COORD_CD": 197008.0,
      "Latitude": 40.707239816000026,
      "Longitude": -73.79272672599996,
      "Lon_Lat": "POINT (-73.79272672599996 40.707239816000026)"
    },
    {
      "ARREST_KEY": 189863002,
      "ARREST_DATE": "2018-11-11 00:00:00",
      "PD_CD": 179,
      "PD_DESC": "SEXUAL ABUSE 1",
      "KY_CD": "116",
      "OFNS_DESC": "SEX CRIMES",
      "LAW_CODE": "PL 1306502",
      "LAW_CAT_CD": "F",
      "ARREST_BORO": "K",
      "ARREST_PRECINCT": "63",
      "JURISDICTION_CODE": 0,
      "AGE_GROUP": "<18",
      "PERP_SEX": "M",
      "PERP_RACE": "BLACK",
      "X_COORD_CD": "1000448",
      "Y_COORD_CD": 168068.0,
      "Latitude": 40.627977755000074,
      "Longitude": -73.94164715699996,
      "Lon_Lat": "POINT (-73.94164715699996 40.62797775500008)"
    },
    {
      "ARREST_KEY": 192148546,
      "ARREST_DATE": "2019-01-10 00:00:00",
      "PD_CD": 168,
      "PD_DESC": "SODOMY 1",
      "KY_CD": "116",
      "OFNS_DESC": "SEX CRIMES",
      "LAW_CODE": "PL 1305003",
      "LAW_CAT_CD": "F",
      "ARREST_BORO": "K",
      "ARREST_PRECINCT": "75",
      "JURISDICTION_CODE": 0,
      "AGE_GROUP": "25-44",
      "PERP_SEX": "M",
      "PERP_RACE": "BLACK",
      "X_COORD_CD": "1017141",
      "Y_COORD_CD": 183798.0,
      "Latitude": 40.67110691100004,
      "Longitude": -73.88143295699996,
      "Lon_Lat": "POINT (-73.88143295699996 40.67110691100004)"
    },
    {
      "ARREST_KEY": 189476017,
      "ARREST_DATE": "2018-11-01 00:00:00",
      "PD_CD": 793,
      "PD_DESC": "WEAPONS POSSESSION 3",
      "KY_CD": "118",
      "OFNS_DESC": "DANGEROUS WEAPONS",
      "LAW_CODE": "PL 2650201",
      "LAW_CAT_CD": "F",
      "ARREST_BORO": "K",
      "ARREST_PRECINCT": "68",
      "JURISDICTION_CODE": 0,
      "AGE_GROUP": "25-44",
      "PERP_SEX": "M",
      "PERP_RACE": "WHITE",
      "X_COORD_CD": "975830",
      "Y_COORD_CD": 164418.0,
      "Latitude": 40.61797007100006,
      "Longitude": -74.03033045599993,
      "Lon_Lat": "POINT (-74.03033045599993 40.617970071000066)"
    },
    {
      "ARREST_KEY": 201100692,
      "ARREST_DATE": "2019-08-14 00:00:00",
      "PD_CD": 105,
      "PD_DESC": "STRANGULATION 1ST",
      "KY_CD": "106",
      "OFNS_DESC": "FELONY ASSAULT",
      "LAW_CODE": "PL 1211200",
      "LAW_CAT_CD": "F",
      "ARREST_BORO": "M",
      "ARREST_PRECINCT": "23",
      "JURISDICTION_CODE": 0,
      "AGE_GROUP": "25-44",
      "PERP_SEX": "M",
      "PERP_RACE": "BLACK",
      "X_COORD_CD": "998829",
      "Y_COORD_CD": 226859.0,
      "Latitude": 40.78934789300007,
      "Longitude": -73.94735241299998,
      "Lon_Lat": "POINT (-73.94735241299998 40.78934789300007)"
    },
    {
      "ARREST_KEY": 237900488,
      "ARREST_DATE": "2021-12-15 00:00:00",
      "PD_CD": 157,
      "PD_DESC": "RAPE 1",
      "KY_CD": "104",
      "OFNS_DESC": "RAPE",
      "LAW_CODE": "PL 1303501",
      "LAW_CAT_CD": "F",
      "ARREST_BORO": "K",
      "ARREST_PRECINCT": "71",
      "JURISDICTION_CODE": 0,
      "AGE_GROUP": "<18",
      "PERP_SEX": "M",
      "PERP_RACE": "BLACK",
      "X_COORD_CD": "998749",
      "Y_COORD_CD": 181383.0,
      "Latitude": 40.66452749800004,
      "Longitude": -73.94773929099993,
      "Lon_Lat": "POINT (-73.94773929099993 40.66452749800004)"
    },
    {
      "ARREST_KEY": 189974181,
      "ARREST_DATE": "2018-11-14 00:00:00",
      "PD_CD": 475,
      "PD_DESC": null,
      "KY_CD": null,
      "OFNS_DESC": null,
      "LAW_CODE": "PL 1651601",
      "LAW_CAT_CD": "M",
      "ARREST_BORO": "M",
      "ARREST_PRECINCT": "14",
      "JURISDICTION_CODE": 1,
      "AGE_GROUP": "65+",
      "PERP_SEX": "M",
      "PERP_RACE": "WHITE",
      "X_COORD_CD": "986061",
      "Y_COORD_CD": 213320.0,
      "Latitude": 40.75219869800003,
      "Longitude": -73.99346504499994,
      "Lon_Lat": "POINT (-73.99346504499994 40.75219869800003)"
    },
    {
      "ARREST_KEY": 193140208,
      "ARREST_DATE": "2019-02-04 00:00:00",
      "PD_CD": 157,
      "PD_DESC": "RAPE 1",
      "KY_CD": "104",
      "OFNS_DESC": "RAPE",
      "LAW_CODE": "PL 1303502",
      "LAW_CAT_CD": "F",
      "ARREST_BORO": "B",
      "ARREST_PRECINCT": "41",
      "JURISDICTION_CODE": 0,
      "AGE_GROUP": "25-44",
      "PERP_SEX": "M",
      "PERP_RACE": "BLACK",
      "X_COORD_CD": "1013232",
      "Y_COORD_CD": 236725.0,
      "Latitude": 40.816391847000034,
      "Longitude": -73.89529641399997,
      "Lon_Lat": "POINT (-73.89529641399997 40.816391847000034)"
    },
    {
      "ARREST_KEY": 237131287,
      "ARREST_DATE": "2021-11-30 00:00:00",
      "PD_CD": 157,
      "PD_DESC": "RAPE 1",
      "KY_CD": "104",
      "OFNS_DESC": "RAPE",
      "LAW_CODE": "PL 1303501",
      "LAW_CAT_CD": "F",
      "ARREST_BORO": "B",
      "ARREST_PRECINCT": "43",
      "JURISDICTION_CODE": 0,
      "AGE_GROUP": "25-44",
      "PERP_SEX": "M",
      "PERP_RACE": "WHITE HISPANIC",
      "X_COORD_CD": "1020316",
      "Y_COORD_CD": 239179.0,
      "Latitude": 40.82310129900002,
      "Longitude": -73.86969046099993,
      "Lon_Lat": "POINT (-73.86969046099993 40.82310129900002)"
    },
    {
      "ARREST_KEY": 193261068,
      "ARREST_DATE": "2019-02-06 00:00:00",
      "PD_CD": 672,
      "PD_DESC": "RIOT 1",
      "KY_CD": "126",
      "OFNS_DESC": "MISCELLANEOUS PENAL LAW",
      "LAW_CODE": "PL 2400601",
      "LAW_CAT_CD": "F",
      "ARREST_BORO": "S",
      "ARREST_PRECINCT": "120",
      "JURISDICTION_CODE": 0,
      "AGE_GROUP": "<18",
      "PERP_SEX": "F",
      "PERP_RACE": "BLACK",
      "X_COORD_CD": "963248",
      "Y_COORD_CD": 173085.0,
      "Latitude": 40.64173826000007,
      "Longitude": -74.07567803699999,
      "Lon_Lat": "POINT (-74.07567803699999 40.641738260000075)"
    },
    {
      "ARREST_KEY": 220752233,
      "ARREST_DATE": "2020-11-19 00:00:00",
      "PD_CD": 166,
      "PD_DESC": "SODOMY 2",
      "KY_CD": "116",
      "OFNS_DESC": "SEX CRIMES",
      "LAW_CODE": "PL 1304501",
      "LAW_CAT_CD": "F",
      "ARREST_BORO": "Q",
      "ARREST_PRECINCT": "109",
      "JURISDICTION_CODE": 0,
      "AGE_GROUP": "25-44",
      "PERP_SEX": "M",
      "PERP_RACE": "WHITE HISPANIC",
      "X_COORD_CD": "1032198",
      "Y_COORD_CD": 217060.0,
      "Latitude": 40.76233421800004,
      "Longitude": -73.82691730799998,
      "Lon_Lat": "POINT (-73.82691730799998 40.76233421800004)"
    },
    {
      "ARREST_KEY": 220709940,
      "ARREST_DATE": "2020-11-19 00:00:00",
      "PD_CD": 157,
      "PD_DESC": "RAPE 1",
      "KY_CD": "104",
      "OFNS_DESC": "RAPE",
      "LAW_CODE": "PL 1303504",
      "LAW_CAT_CD": "F",
      "ARREST_BORO": "M",
      "ARREST_PRECINCT": "28",
      "JURISDICTION_CODE": 0,
      "AGE_GROUP": "<18",
      "PERP_SEX": "M",
      "PERP_RACE": "BLACK",
      "X_COORD_CD": "997376",
      "Y_COORD_CD": 233927.0,
      "Latitude": 40.80874990400008,
      "Longitude": -73.95258580599993,
      "Lon_Lat": "POINT (-73.95258580599993 40.80874990400008)"
    },
    {
      "ARREST_KEY": 74763647,
      "ARREST_DATE": "2010-09-24 00:00:00",
      "PD_CD": 153,
      "PD_DESC": "RAPE 3",
      "KY_CD": "104",
      "OFNS_DESC": "RAPE",
      "LAW_CODE": "PL 1302502",
      "LAW_CAT_CD": "F",
      "ARREST_BORO": "M",
      "ARREST_PRECINCT": "25",
      "JURISDICTION_CODE": 0,
      "AGE_GROUP": "45-64",
      "PERP_SEX": "M",
      "PERP_RACE": "WHITE HISPANIC",
      "X_COORD_CD": "1000555.0",
      "Y_COORD_CD": 230994.0,
      "Latitude": 40.800694331000045,
      "Longitude": -73.94110928599997,
      "Lon_Lat": "POINT (-73.94110928599997 40.800694331000045)"
    },
    {
      "ARREST_KEY": 220342612,
      "ARREST_DATE": "2020-11-10 00:00:00",
      "PD_CD": 155,
      "PD_DESC": "RAPE 2",
      "KY_CD": "104",
      "OFNS_DESC": "RAPE",
      "LAW_CODE": "PL 1303001",
      "LAW_CAT_CD": "F",
      "ARREST_BORO": "M",
      "ARREST_PRECINCT": "5",
      "JURISDICTION_CODE": 0,
      "AGE_GROUP": "25-44",
      "PERP_SEX": "M",
      "PERP_RACE": "BLACK",
      "X_COORD_CD": "984946",
      "Y_COORD_CD": 200203.0,
      "Latitude": 40.716195914000025,
      "Longitude": -73.99749074599998,
      "Lon_Lat": "POINT (-73.99749074599998 40.716195914000025)"
    },
    {
      "ARREST_KEY": 237762927,
      "ARREST_DATE": "2021-12-13 00:00:00",
      "PD_CD": 155,
      "PD_DESC": "RAPE 2",
      "KY_CD": "104",
      "OFNS_DESC": "RAPE",
      "LAW_CODE": "PL 1303001",
      "LAW_CAT_CD": "F",
      "ARREST_BORO": "Q",
      "ARREST_PRECINCT": "114",
      "JURISDICTION_CODE": 0,
      "AGE_GROUP": "45-64",
      "PERP_SEX": "M",
      "PERP_RACE": "WHITE",
      "X_COORD_CD": "1007654",
      "Y_COORD_CD": 219564.0,
      "Latitude": 40.76930608700008,
      "Longitude": -73.91550817999997,
      "Lon_Lat": "POINT (-73.91550817999997 40.76930608700008)"
    },
    {
      "ARREST_KEY": 190140531,
      "ARREST_DATE": "2018-11-18 00:00:00",
      "PD_CD": 153,
      "PD_DESC": "RAPE 3",
      "KY_CD": "104",
      "OFNS_DESC": "RAPE",
      "LAW_CODE": "PL 1302501",
      "LAW_CAT_CD": "F",
      "ARREST_BORO": "B",
      "ARREST_PRECINCT": "44",
      "JURISDICTION_CODE": 0,
      "AGE_GROUP": "18-24",
      "PERP_SEX": "M",
      "PERP_RACE": "WHITE HISPANIC",
      "X_COORD_CD": "1006434",
      "Y_COORD_CD": 244344.0,
      "Latitude": 40.83732351100008,
      "Longitude": -73.91983075699994,
      "Lon_Lat": "POINT (-73.91983075699994 40.83732351100008)"
    },
    {
      "ARREST_KEY": 188086111,
      "ARREST_DATE": "2018-09-27 00:00:00",
      "PD_CD": null,
      "PD_DESC": null,
      "KY_CD": null,
      "OFNS_DESC": null,
      "LAW_CODE": null,
      "LAW_CAT_CD": null,
      "ARREST_BORO": "B",
      "ARREST_PRECINCT": "50",
      "JURISDICTION_CODE": 0,
      "AGE_GROUP": "25-44",
      "PERP_SEX": "M",
      "PERP_RACE": "WHITE HISPANIC",
      "X_COORD_CD": "1012688",
      "Y_COORD_CD": 270928.0,
      "Latitude": 40.91027045300007,
      "Longitude": -73.89711662799994,
      "Lon_Lat": "POINT (-73.89711662799994 40.91027045300007)"
    },
    {
      "ARREST_KEY": 203540310,
      "ARREST_DATE": "2019-10-10 00:00:00",
      "PD_CD": 164,
      "PD_DESC": "SODOMY 3",
      "KY_CD": "116",
      "OFNS_DESC": "SEX CRIMES",
      "LAW_CODE": "PL 1304003",
      "LAW_CAT_CD": "F",
      "ARREST_BORO": "M",
      "ARREST_PRECINCT": "13",
      "JURISDICTION_CODE": 1,
      "AGE_GROUP": "25-44",
      "PERP_SEX": "M",
      "PERP_RACE": "WHITE HISPANIC",
      "X_COORD_CD": "988874",
      "Y_COORD_CD": 207673.0,
      "Latitude": 40.736698070000045,
      "Longitude": -73.98331602599995,
      "Lon_Lat": "POINT (-73.98331602599995 40.736698070000045)"
    },
    {
      "ARREST_KEY": 191717184,
      "ARREST_DATE": "2019-01-01 00:00:00",
      "PD_CD": 105,
      "PD_DESC": "STRANGULATION 1ST",
      "KY_CD": "106",
      "OFNS_DESC": "FELONY ASSAULT",
      "LAW_CODE": "PL 1211200",
      "LAW_CAT_CD": "F",
      "ARREST_BORO": "K",
      "ARREST_PRECINCT": "68",
      "JURISDICTION_CODE": 0,
      "AGE_GROUP": "45-64",
      "PERP_SEX": "F",
      "PERP_RACE": "WHITE",
      "X_COORD_CD": "982473",
      "Y_COORD_CD": 168770.0,
      "Latitude": 40.62991922600003,
      "Longitude": -74.00640337899995,
      "Lon_Lat": "POINT (-74.00640337899995 40.62991922600003)"
    },
    {
      "ARREST_KEY": 236067007,
      "ARREST_DATE": "2021-11-09 00:00:00",
      "PD_CD": 157,
      "PD_DESC": "RAPE 1",
      "KY_CD": "104",
      "OFNS_DESC": "RAPE",
      "LAW_CODE": "PL 1303504",
      "LAW_CAT_CD": "F",
      "ARREST_BORO": "Q",
      "ARREST_PRECINCT": "112",
      "JURISDICTION_CODE": 0,
      "AGE_GROUP": "18-24",
      "PERP_SEX": "M",
      "PERP_RACE": "WHITE HISPANIC",
      "X_COORD_CD": "1025420",
      "Y_COORD_CD": 202485.0,
      "Latitude": 40.72236368700004,
      "Longitude": -73.85147389399998,
      "Lon_Lat": "POINT (-73.85147389399998 40.72236368700004)"
    },
    {
      "ARREST_KEY": 238135306,
      "ARREST_DATE": "2021-12-21 00:00:00",
      "PD_CD": 155,
      "PD_DESC": "RAPE 2",
      "KY_CD": "104",
      "OFNS_DESC": "RAPE",
      "LAW_CODE": "PL 1303001",
      "LAW_CAT_CD": "F",
      "ARREST_BORO": "Q",
      "ARREST_PRECINCT": "112",
      "JURISDICTION_CODE": 0,
      "AGE_GROUP": "25-44",
      "PERP_SEX": "M",
      "PERP_RACE": "BLACK",
      "X_COORD_CD": "1025420",
      "Y_COORD_CD": 202485.0,
      "Latitude": 40.72236368700004,
      "Longitude": -73.85147389399998,
      "Lon_Lat": "POINT (-73.85147389399998 40.72236368700004)"
    },
    {
      "ARREST_KEY": 186712976,
      "ARREST_DATE": "2018-08-22 00:00:00",
      "PD_CD": 475,
      "PD_DESC": null,
      "KY_CD": null,
      "OFNS_DESC": null,
      "LAW_CODE": "PL 1651601",
      "LAW_CAT_CD": "M",
      "ARREST_BORO": "Q",
      "ARREST_PRECINCT": "103",
      "JURISDICTION_CODE": 1,
      "AGE_GROUP": "25-44",
      "PERP_SEX": "M",
      "PERP_RACE": "BLACK",
      "X_COORD_CD": "1037559",
      "Y_COORD_CD": 194576.0,
      "Latitude": 40.70059059000005,
      "Longitude": -73.80774319999993,
      "Lon_Lat": "POINT (-73.80774319999995 40.70059059000005)"
    },
    {
      "ARREST_KEY": 192038498,
      "ARREST_DATE": "2019-01-08 00:00:00",
      "PD_CD": 117,
      "PD_DESC": "RECKLESS ENDANGERMENT 1",
      "KY_CD": "126",
      "OFNS_DESC": "MISCELLANEOUS PENAL LAW",
      "LAW_CODE": "PL 1202500",
      "LAW_CAT_CD": "F",
      "ARREST_BORO": "Q",
      "ARREST_PRECINCT": "101",
      "JURISDICTION_CODE": 0,
      "AGE_GROUP": "18-24",
      "PERP_SEX": "M",
      "PERP_RACE": "BLACK",
      "X_COORD_CD": "1050061",
      "Y_COORD_CD": 158942.0,
      "Latitude": 40.60269922100008,
      "Longitude": -73.76300278499997,
      "Lon_Lat": "POINT (-73.76300278499997 40.60269922100008)"
    },
    {
      "ARREST_KEY": 192068590,
      "ARREST_DATE": "2019-01-09 00:00:00",
      "PD_CD": 793,
      "PD_DESC": "WEAPONS POSSESSION 3",
      "KY_CD": "118",
      "OFNS_DESC": "DANGEROUS WEAPONS",
      "LAW_CODE": "PL 2650201",
      "LAW_CAT_CD": "F",
      "ARREST_BORO": "K",
      "ARREST_PRECINCT": "68",
      "JURISDICTION_CODE": 0,
      "AGE_GROUP": "25-44",
      "PERP_SEX": "F",
      "PERP_RACE": "BLACK",
      "X_COORD_CD": "976209",
      "Y_COORD_CD": 165633.0,
      "Latitude": 40.62130534600004,
      "Longitude": -74.02896673699996,
      "Lon_Lat": "POINT (-74.02896673699996 40.62130534600004)"
    },
    {
      "ARREST_KEY": 221443815,
      "ARREST_DATE": "2020-12-06 00:00:00",
      "PD_CD": 157,
      "PD_DESC": "RAPE 1",
      "KY_CD": "104",
      "OFNS_DESC": "RAPE",
      "LAW_CODE": "PL 1303501",
      "LAW_CAT_CD": "F",
      "ARREST_BORO": "K",
      "ARREST_PRECINCT": "67",
      "JURISDICTION_CODE": 0,
      "AGE_GROUP": "18-24",
      "PERP_SEX": "M",
      "PERP_RACE": "BLACK",
      "X_COORD_CD": "998032",
      "Y_COORD_CD": 175598.0,
      "Latitude": 40.648650085000035,
      "Longitude": -73.95033556299995,
      "Lon_Lat": "POINT (-73.95033556299995 40.648650085000035)"
    },
    {
      "ARREST_KEY": 237431980,
      "ARREST_DATE": "2021-12-06 00:00:00",
      "PD_CD": 105,
      "PD_DESC": "STRANGULATION 1ST",
      "KY_CD": "106",
      "OFNS_DESC": "FELONY ASSAULT",
      "LAW_CODE": "PL 1211200",
      "LAW_CAT_CD": "F",
      "ARREST_BORO": "K",
      "ARREST_PRECINCT": "60",
      "JURISDICTION_CODE": 0,
      "AGE_GROUP": "25-44",
      "PERP_SEX": "M",
      "PERP_RACE": "WHITE",
      "X_COORD_CD": "993768",
      "Y_COORD_CD": 149165.0,
      "Latitude": 40.57610255100008,
      "Longitude": -73.96573889499997,
      "Lon_Lat": "POINT (-73.96573889499997 40.57610255100008)"
    },
    {
      "ARREST_KEY": 237783773,
      "ARREST_DATE": "2021-12-13 00:00:00",
      "PD_CD": 153,
      "PD_DESC": "RAPE 3",
      "KY_CD": "104",
      "OFNS_DESC": "RAPE",
      "LAW_CODE": "PL 1302502",
      "LAW_CAT_CD": "F",
      "ARREST_BORO": "B",
      "ARREST_PRECINCT": "52",
      "JURISDICTION_CODE": 0,
      "AGE_GROUP": "25-44",
      "PERP_SEX": "M",
      "PERP_RACE": "WHITE",
      "X_COORD_CD": "1017542",
      "Y_COORD_CD": 255919.0,
      "Latitude": 40.86905853200005,
      "Longitude": -73.87963014799993,
      "Lon_Lat": "POINT (-73.87963014799993 40.86905853200005)"
    },
    {
      "ARREST_KEY": 195423173,
      "ARREST_DATE": "2019-04-01 00:00:00",
      "PD_CD": 157,
      "PD_DESC": "RAPE 1",
      "KY_CD": "104",
      "OFNS_DESC": "RAPE",
      "LAW_CODE": "PL 1303502",
      "LAW_CAT_CD": "F",
      "ARREST_BORO": "B",
      "ARREST_PRECINCT": "41",
      "JURISDICTION_CODE": 0,
      "AGE_GROUP": "18-24",
      "PERP_SEX": "M",
      "PERP_RACE": "BLACK",
      "X_COORD_CD": "1013232",
      "Y_COORD_CD": 236725.0,
      "Latitude": 40.816391847000034,
      "Longitude": -73.89529641399997,
      "Lon_Lat": "POINT (-73.89529641399997 40.816391847000034)"
    },
    {
      "ARREST_KEY": 237072001,
      "ARREST_DATE": "2021-11-29 00:00:00",
      "PD_CD": 578,
      "PD_DESC": null,
      "KY_CD": null,
      "OFNS_DESC": null,
      "LAW_CODE": "PL 2223001",
      "LAW_CAT_CD": "M",
      "ARREST_BORO": "K",
      "ARREST_PRECINCT": "84",
      "JURISDICTION_CODE": 0,
      "AGE_GROUP": "25-44",
      "PERP_SEX": "M",
      "PERP_RACE": "BLACK",
      "X_COORD_CD": "987778",
      "Y_COORD_CD": 191639.0,
      "Latitude": 40.69268906900004,
      "Longitude": -73.98727927499993,
      "Lon_Lat": "POINT (-73.98727927499993 40.69268906900004)"
    },
    {
      "ARREST_KEY": 193170391,
      "ARREST_DATE": "2019-02-05 00:00:00",
      "PD_CD": 153,
      "PD_DESC": "RAPE 3",
      "KY_CD": "104",
      "OFNS_DESC": "RAPE",
      "LAW_CODE": "PL 1302502",
      "LAW_CAT_CD": "F",
      "ARREST_BORO": "Q",
      "ARREST_PRECINCT": "112",
      "JURISDICTION_CODE": 0,
      "AGE_GROUP": "25-44",
      "PERP_SEX": "M",
      "PERP_RACE": "BLACK",
      "X_COORD_CD": "1025420",
      "Y_COORD_CD": 202485.0,
      "Latitude": 40.72236368700004,
      "Longitude": -73.85147389399998,
      "Lon_Lat": "POINT (-73.85147389399998 40.72236368700005)"
    },
    {
      "ARREST_KEY": 221839503,
      "ARREST_DATE": "2020-12-14 00:00:00",
      "PD_CD": 155,
      "PD_DESC": "RAPE 2",
      "KY_CD": "104",
      "OFNS_DESC": "RAPE",
      "LAW_CODE": "PL 1303001",
      "LAW_CAT_CD": "F",
      "ARREST_BORO": "B",
      "ARREST_PRECINCT": "46",
      "JURISDICTION_CODE": 0,
      "AGE_GROUP": "25-44",
      "PERP_SEX": "M",
      "PERP_RACE": "WHITE HISPANIC",
      "X_COORD_CD": "1011881",
      "Y_COORD_CD": 250411.0,
      "Latitude": 40.85396027400003,
      "Longitude": -73.90012087499997,
      "Lon_Lat": "POINT (-73.90012087499997 40.85396027400004)"
    },
    {
      "ARREST_KEY": 237172828,
      "ARREST_DATE": "2021-12-01 00:00:00",
      "PD_CD": 153,
      "PD_DESC": "RAPE 3",
      "KY_CD": "104",
      "OFNS_DESC": "RAPE",
      "LAW_CODE": "PL 1302503",
      "LAW_CAT_CD": "F",
      "ARREST_BORO": "K",
      "ARREST_PRECINCT": "77",
      "JURISDICTION_CODE": 0,
      "AGE_GROUP": "25-44",
      "PERP_SEX": "M",
      "PERP_RACE": "WHITE HISPANIC",
      "X_COORD_CD": "1003606",
      "Y_COORD_CD": 185050.0,
      "Latitude": 40.67458330800008,
      "Longitude": -73.93022154099998,
      "Lon_Lat": "POINT (-73.93022154099998 40.67458330800008)"
    },
    {
      "ARREST_KEY": 189263596,
      "ARREST_DATE": "2018-10-27 00:00:00",
      "PD_CD": 101,
      "PD_DESC": "ASSAULT 3",
      "KY_CD": "344",
      "OFNS_DESC": "ASSAULT 3 & RELATED OFFENSES",
      "LAW_CODE": "PL 1200001",
      "LAW_CAT_CD": "M",
      "ARREST_BORO": "B",
      "ARREST_PRECINCT": "44",
      "JURISDICTION_CODE": 0,
      "AGE_GROUP": "25-44",
      "PERP_SEX": "M",
      "PERP_RACE": "BLACK",
      "X_COORD_CD": "1008173",
      "Y_COORD_CD": 241622.0,
      "Latitude": 40.82984786900005,
      "Longitude": -73.91355590099994,
      "Lon_Lat": "POINT (-73.91355590099994 40.82984786900005)"
    },
    {
      "ARREST_KEY": 205007433,
      "ARREST_DATE": "2019-11-11 00:00:00",
      "PD_CD": 105,
      "PD_DESC": "STRANGULATION 1ST",
      "KY_CD": "106",
      "OFNS_DESC": "FELONY ASSAULT",
      "LAW_CODE": "PL 1211200",
      "LAW_CAT_CD": "F",
      "ARREST_BORO": "K",
      "ARREST_PRECINCT": "71",
      "JURISDICTION_CODE": 0,
      "AGE_GROUP": "25-44",
      "PERP_SEX": "M",
      "PERP_RACE": "BLACK",
      "X_COORD_CD": "995254",
      "Y_COORD_CD": 181232.0,
      "Latitude": 40.66411807000003,
      "Longitude": -73.96033738499995,
      "Lon_Lat": "POINT (-73.96033738499995 40.66411807000003)"
    },
    {
      "ARREST_KEY": 191797394,
      "ARREST_DATE": "2019-01-03 00:00:00",
      "PD_CD": 792,
      "PD_DESC": "WEAPONS POSSESSION 1 & 2",
      "KY_CD": "118",
      "OFNS_DESC": "DANGEROUS WEAPONS",
      "LAW_CODE": "PL 265031B",
      "LAW_CAT_CD": "F",
      "ARREST_BORO": "B",
      "ARREST_PRECINCT": "40",
      "JURISDICTION_CODE": 0,
      "AGE_GROUP": "18-24",
      "PERP_SEX": "F",
      "PERP_RACE": "BLACK",
      "X_COORD_CD": "1009057",
      "Y_COORD_CD": 237122.0,
      "Latitude": 40.81749421000006,
      "Longitude": -73.91037821299994,
      "Lon_Lat": "POINT (-73.91037821299994 40.81749421000006)"
    },
    {
      "ARREST_KEY": 190025272,
      "ARREST_DATE": "2018-11-15 00:00:00",
      "PD_CD": 157,
      "PD_DESC": "RAPE 1",
      "KY_CD": "104",
      "OFNS_DESC": "RAPE",
      "LAW_CODE": "PL 1303501",
      "LAW_CAT_CD": "F",
      "ARREST_BORO": "B",
      "ARREST_PRECINCT": "41",
      "JURISDICTION_CODE": 0,
      "AGE_GROUP": "25-44",
      "PERP_SEX": "M",
      "PERP_RACE": "BLACK",
      "X_COORD_CD": "1013232",
      "Y_COORD_CD": 236725.0,
      "Latitude": 40.816391847000034,
      "Longitude": -73.89529641399997,
      "Lon_Lat": "POINT (-73.89529641399997 40.816391847000034)"
    },
    {
      "ARREST_KEY": 236831794,
      "ARREST_DATE": "2021-11-23 00:00:00",
      "PD_CD": 105,
      "PD_DESC": "STRANGULATION 1ST",
      "KY_CD": "106",
      "OFNS_DESC": "FELONY ASSAULT",
      "LAW_CODE": "PL 1211200",
      "LAW_CAT_CD": "F",
      "ARREST_BORO": "K",
      "ARREST_PRECINCT": "79",
      "JURISDICTION_CODE": 0,
      "AGE_GROUP": "18-24",
      "PERP_SEX": "M",
      "PERP_RACE": "BLACK",
      "X_COORD_CD": "999507",
      "Y_COORD_CD": 190206.0,
      "Latitude": 40.688743368000075,
      "Longitude": -73.94498708099997,
      "Lon_Lat": "POINT (-73.94498708099997 40.688743368000075)"
    },
    {
      "ARREST_KEY": 191751269,
      "ARREST_DATE": "2019-01-02 00:00:00",
      "PD_CD": 157,
      "PD_DESC": "RAPE 1",
      "KY_CD": "104",
      "OFNS_DESC": "RAPE",
      "LAW_CODE": "PL 1303501",
      "LAW_CAT_CD": "F",
      "ARREST_BORO": "S",
      "ARREST_PRECINCT": "121",
      "JURISDICTION_CODE": 0,
      "AGE_GROUP": "25-44",
      "PERP_SEX": "M",
      "PERP_RACE": "WHITE HISPANIC",
      "X_COORD_CD": "942428",
      "Y_COORD_CD": 166536.0,
      "Latitude": 40.62368882200008,
      "Longitude": -74.15065813299998,
      "Lon_Lat": "POINT (-74.15065813299998 40.62368882200008)"
    },
    {
      "ARREST_KEY": 189168192,
      "ARREST_DATE": "2018-10-24 00:00:00",
      "PD_CD": 155,
      "PD_DESC": "RAPE 2",
      "KY_CD": "104",
      "OFNS_DESC": "RAPE",
      "LAW_CODE": "PL 1303001",
      "LAW_CAT_CD": "F",
      "ARREST_BORO": "M",
      "ARREST_PRECINCT": "1",
      "JURISDICTION_CODE": 0,
      "AGE_GROUP": "18-24",
      "PERP_SEX": "M",
      "PERP_RACE": "WHITE",
      "X_COORD_CD": "982285",
      "Y_COORD_CD": 201682.0,
      "Latitude": 40.72025522300004,
      "Longitude": -74.00709027999993,
      "Lon_Lat": "POINT (-74.00709027999993 40.72025522300004)"
    },
    {
      "ARREST_KEY": 234630426,
      "ARREST_DATE": "2021-10-07 00:00:00",
      "PD_CD": 157,
      "PD_DESC": "RAPE 1",
      "KY_CD": "104",
      "OFNS_DESC": "RAPE",
      "LAW_CODE": "PL 1303502",
      "LAW_CAT_CD": "F",
      "ARREST_BORO": "B",
      "ARREST_PRECINCT": "43",
      "JURISDICTION_CODE": 0,
      "AGE_GROUP": "25-44",
      "PERP_SEX": "M",
      "PERP_RACE": "BLACK",
      "X_COORD_CD": "1020316",
      "Y_COORD_CD": 239179.0,
      "Latitude": 40.82310129900002,
      "Longitude": -73.86969046099993,
      "Lon_Lat": "POINT (-73.86969046099993 40.82310129900002)"
    },
    {
      "ARREST_KEY": 194014492,
      "ARREST_DATE": "2019-02-26 00:00:00",
      "PD_CD": 155,
      "PD_DESC": "RAPE 2",
      "KY_CD": "104",
      "OFNS_DESC": "RAPE",
      "LAW_CODE": "PL 1303001",
      "LAW_CAT_CD": "F",
      "ARREST_BORO": "M",
      "ARREST_PRECINCT": "25",
      "JURISDICTION_CODE": 0,
      "AGE_GROUP": "25-44",
      "PERP_SEX": "M",
      "PERP_RACE": "WHITE HISPANIC",
      "X_COORD_CD": "1000555",
      "Y_COORD_CD": 230994.0,
      "Latitude": 40.800694331000045,
      "Longitude": -73.94110928599997,
      "Lon_Lat": "POINT (-73.94110928599997 40.800694331000045)"
    },
    {
      "ARREST_KEY": 191917898,
      "ARREST_DATE": "2019-01-05 00:00:00",
      "PD_CD": 793,
      "PD_DESC": "WEAPONS POSSESSION 3",
      "KY_CD": "118",
      "OFNS_DESC": "DANGEROUS WEAPONS",
      "LAW_CODE": "PL 2650201",
      "LAW_CAT_CD": "F",
      "ARREST_BORO": "M",
      "ARREST_PRECINCT": "14",
      "JURISDICTION_CODE": 7,
      "AGE_GROUP": "25-44",
      "PERP_SEX": "M",
      "PERP_RACE": "BLACK",
      "X_COORD_CD": "986320",
      "Y_COORD_CD": 212857.0,
      "Latitude": 40.75092782300004,
      "Longitude": -73.99253038399996,
      "Lon_Lat": "POINT (-73.99253038399996 40.75092782300004)"
    },
    {
      "ARREST_KEY": 193524566,
      "ARREST_DATE": "2019-02-13 00:00:00",
      "PD_CD": 153,
      "PD_DESC": "RAPE 3",
      "KY_CD": "104",
      "OFNS_DESC": "RAPE",
      "LAW_CODE": "PL 1302501",
      "LAW_CAT_CD": "F",
      "ARREST_BORO": "K",
      "ARREST_PRECINCT": "77",
      "JURISDICTION_CODE": 0,
      "AGE_GROUP": "18-24",
      "PERP_SEX": "M",
      "PERP_RACE": "WHITE",
      "X_COORD_CD": "1003606",
      "Y_COORD_CD": 185050.0,
      "Latitude": 40.67458330800008,
      "Longitude": -73.93022154099998,
      "Lon_Lat": "POINT (-73.93022154099998 40.67458330800008)"
    },
    {
      "ARREST_KEY": 191943063,
      "ARREST_DATE": "2019-01-06 00:00:00",
      "PD_CD": null,
      "PD_DESC": null,
      "KY_CD": null,
      "OFNS_DESC": null,
      "LAW_CODE": "PL 2203400",
      "LAW_CAT_CD": "F",
      "ARREST_BORO": "M",
      "ARREST_PRECINCT": "9",
      "JURISDICTION_CODE": 0,
      "AGE_GROUP": "25-44",
      "PERP_SEX": "M",
      "PERP_RACE": "WHITE",
      "X_COORD_CD": "990294",
      "Y_COORD_CD": 203412.0,
      "Latitude": 40.72500181100003,
      "Longitude": -73.97819586899993,
      "Lon_Lat": "POINT (-73.97819586899993 40.72500181100003)"
    },
    {
      "ARREST_KEY": 234758787,
      "ARREST_DATE": "2021-10-10 00:00:00",
      "PD_CD": 168,
      "PD_DESC": "SODOMY 1",
      "KY_CD": "116",
      "OFNS_DESC": "SEX CRIMES",
      "LAW_CODE": "PL 1305001",
      "LAW_CAT_CD": "F",
      "ARREST_BORO": "M",
      "ARREST_PRECINCT": "7",
      "JURISDICTION_CODE": 0,
      "AGE_GROUP": "45-64",
      "PERP_SEX": "M",
      "PERP_RACE": "BLACK",
      "X_COORD_CD": "988708",
      "Y_COORD_CD": 200317.0,
      "Latitude": 40.71650772200008,
      "Longitude": -73.98391989899994,
      "Lon_Lat": "POINT (-73.98391989899994 40.71650772200008)"
    },
    {
      "ARREST_KEY": 219169035,
      "ARREST_DATE": "2020-10-14 00:00:00",
      "PD_CD": 157,
      "PD_DESC": "RAPE 1",
      "KY_CD": "104",
      "OFNS_DESC": "RAPE",
      "LAW_CODE": "PL 1303504",
      "LAW_CAT_CD": "F",
      "ARREST_BORO": "K",
      "ARREST_PRECINCT": "84",
      "JURISDICTION_CODE": 0,
      "AGE_GROUP": "45-64",
      "PERP_SEX": "M",
      "PERP_RACE": "BLACK",
      "X_COORD_CD": "989013",
      "Y_COORD_CD": 192652.0,
      "Latitude": 40.69546894100006,
      "Longitude": -73.98282507899995,
      "Lon_Lat": "POINT (-73.98282507899995 40.69546894100006)"
    },
    {
      "ARREST_KEY": 217780910,
      "ARREST_DATE": "2020-09-14 00:00:00",
      "PD_CD": 101,
      "PD_DESC": "ASSAULT 3",
      "KY_CD": "344",
      "OFNS_DESC": "ASSAULT 3 & RELATED OFFENSES",
      "LAW_CODE": "PL 1200001",
      "LAW_CAT_CD": "M",
      "ARREST_BORO": "K",
      "ARREST_PRECINCT": "75",
      "JURISDICTION_CODE": 0,
      "AGE_GROUP": "18-24",
      "PERP_SEX": "M",
      "PERP_RACE": "BLACK",
      "X_COORD_CD": "1019819",
      "Y_COORD_CD": 185857.0,
      "Latitude": 40.676748045000075,
      "Longitude": -73.87176820599996,
      "Lon_Lat": "POINT (-73.87176820599997 40.676748045000075)"
    },
    {
      "ARREST_KEY": 234208803,
      "ARREST_DATE": "2021-09-29 00:00:00",
      "PD_CD": 578,
      "PD_DESC": null,
      "KY_CD": null,
      "OFNS_DESC": null,
      "LAW_CODE": "PL 2223001",
      "LAW_CAT_CD": "M",
      "ARREST_BORO": "Q",
      "ARREST_PRECINCT": "105",
      "JURISDICTION_CODE": 0,
      "AGE_GROUP": "25-44",
      "PERP_SEX": "M",
      "PERP_RACE": "BLACK",
      "X_COORD_CD": "1057738",
      "Y_COORD_CD": 204079.0,
      "Latitude": 40.72652937700008,
      "Longitude": -73.73486453799995,
      "Lon_Lat": "POINT (-73.73486453799995 40.72652937700008)"
    },
    {
      "ARREST_KEY": 192399624,
      "ARREST_DATE": "2019-01-16 00:00:00",
      "PD_CD": 153,
      "PD_DESC": "RAPE 3",
      "KY_CD": "104",
      "OFNS_DESC": "RAPE",
      "LAW_CODE": "PL 1302501",
      "LAW_CAT_CD": "F",
      "ARREST_BORO": "M",
      "ARREST_PRECINCT": "18",
      "JURISDICTION_CODE": 0,
      "AGE_GROUP": "18-24",
      "PERP_SEX": "M",
      "PERP_RACE": "BLACK",
      "X_COORD_CD": "988353",
      "Y_COORD_CD": 217918.0,
      "Latitude": 40.764818269000045,
      "Longitude": -73.98518977299995,
      "Lon_Lat": "POINT (-73.98518977299995 40.764818269000045)"
    },
    {
      "ARREST_KEY": 217773967,
      "ARREST_DATE": "2020-09-13 00:00:00",
      "PD_CD": 168,
      "PD_DESC": "SODOMY 1",
      "KY_CD": "116",
      "OFNS_DESC": "SEX CRIMES",
      "LAW_CODE": "PL 1305001",
      "LAW_CAT_CD": "F",
      "ARREST_BORO": "K",
      "ARREST_PRECINCT": "90",
      "JURISDICTION_CODE": 0,
      "AGE_GROUP": "<18",
      "PERP_SEX": "M",
      "PERP_RACE": "BLACK HISPANIC",
      "X_COORD_CD": "997843",
      "Y_COORD_CD": 196573.0,
      "Latitude": 40.70622201300005,
      "Longitude": -73.95097435599996,
      "Lon_Lat": "POINT (-73.95097435599996 40.70622201300005)"
    },
    {
      "ARREST_KEY": 188210546,
      "ARREST_DATE": "2018-10-01 00:00:00",
      "PD_CD": 665,
      "PD_DESC": null,
      "KY_CD": null,
      "OFNS_DESC": null,
      "LAW_CODE": "PL 4902001",
      "LAW_CAT_CD": "F",
      "ARREST_BORO": "K",
      "ARREST_PRECINCT": "61",
      "JURISDICTION_CODE": 0,
      "AGE_GROUP": "<18",
      "PERP_SEX": "M",
      "PERP_RACE": "WHITE",
      "X_COORD_CD": "995118",
      "Y_COORD_CD": 155709.0,
      "Latitude": 40.59406298000005,
      "Longitude": -73.96086869299995,
      "Lon_Lat": "POINT (-73.96086869299995 40.59406298000005)"
    },
    {
      "ARREST_KEY": 192389746,
      "ARREST_DATE": "2019-01-16 00:00:00",
      "PD_CD": null,
      "PD_DESC": null,
      "KY_CD": null,
      "OFNS_DESC": null,
      "LAW_CODE": "PL 2203400",
      "LAW_CAT_CD": "F",
      "ARREST_BORO": "M",
      "ARREST_PRECINCT": "14",
      "JURISDICTION_CODE": 0,
      "AGE_GROUP": "45-64",
      "PERP_SEX": "M",
      "PERP_RACE": "WHITE",
      "X_COORD_CD": "986061",
      "Y_COORD_CD": 213320.0,
      "Latitude": 40.75219869800003,
      "Longitude": -73.99346504499994,
      "Lon_Lat": "POINT (-73.99346504499994 40.75219869800003)"
    },
    {
      "ARREST_KEY": 219168747,
      "ARREST_DATE": "2020-10-14 00:00:00",
      "PD_CD": 157,
      "PD_DESC": "RAPE 1",
      "KY_CD": "104",
      "OFNS_DESC": "RAPE",
      "LAW_CODE": "PL 1303502",
      "LAW_CAT_CD": "F",
      "ARREST_BORO": "K",
      "ARREST_PRECINCT": "77",
      "JURISDICTION_CODE": 0,
      "AGE_GROUP": "25-44",
      "PERP_SEX": "M",
      "PERP_RACE": "BLACK",
      "X_COORD_CD": "1003606",
      "Y_COORD_CD": 185050.0,
      "Latitude": 40.67458330800008,
      "Longitude": -73.93022154099998,
      "Lon_Lat": "POINT (-73.93022154099998 40.67458330800008)"
    },
    {
      "ARREST_KEY": 188086113,
      "ARREST_DATE": "2018-09-27 00:00:00",
      "PD_CD": null,
      "PD_DESC": null,
      "KY_CD": null,
      "OFNS_DESC": null,
      "LAW_CODE": null,
      "LAW_CAT_CD": null,
      "ARREST_BORO": "B",
      "ARREST_PRECINCT": "50",
      "JURISDICTION_CODE": 0,
      "AGE_GROUP": "25-44",
      "PERP_SEX": "M",
      "PERP_RACE": "WHITE HISPANIC",
      "X_COORD_CD": "1012688",
      "Y_COORD_CD": 270928.0,
      "Latitude": 40.91027045300007,
      "Longitude": -73.89711662799994,
      "Lon_Lat": "POINT (-73.89711662799994 40.91027045300007)"
    },
    {
      "ARREST_KEY": 234699518,
      "ARREST_DATE": "2021-10-08 00:00:00",
      "PD_CD": 101,
      "PD_DESC": "ASSAULT 3",
      "KY_CD": "344",
      "OFNS_DESC": "ASSAULT 3 & RELATED OFFENSES",
      "LAW_CODE": "PL 1200001",
      "LAW_CAT_CD": "M",
      "ARREST_BORO": "K",
      "ARREST_PRECINCT": "79",
      "JURISDICTION_CODE": 0,
      "AGE_GROUP": "18-24",
      "PERP_SEX": "F",
      "PERP_RACE": "BLACK",
      "X_COORD_CD": "1000922",
      "Y_COORD_CD": 186700.0,
      "Latitude": 40.67911764600007,
      "Longitude": -73.93989348699995,
      "Lon_Lat": "POINT (-73.93989348699995 40.67911764600007)"
    },
    {
      "ARREST_KEY": 206009619,
      "ARREST_DATE": "2019-12-04 00:00:00",
      "PD_CD": 440,
      "PD_DESC": null,
      "KY_CD": null,
      "OFNS_DESC": null,
      "LAW_CODE": "PL 1553502",
      "LAW_CAT_CD": "F",
      "ARREST_BORO": "Q",
      "ARREST_PRECINCT": "114",
      "JURISDICTION_CODE": 0,
      "AGE_GROUP": "<18",
      "PERP_SEX": "M",
      "PERP_RACE": "WHITE",
      "X_COORD_CD": "1009988",
      "Y_COORD_CD": 221743.0,
      "Latitude": 40.77528038400004,
      "Longitude": -73.90707361899996,
      "Lon_Lat": "POINT (-73.90707361899996 40.77528038400004)"
    },
    {
      "ARREST_KEY": 192751854,
      "ARREST_DATE": "2019-01-25 00:00:00",
      "PD_CD": 440,
      "PD_DESC": null,
      "KY_CD": null,
      "OFNS_DESC": null,
      "LAW_CODE": "PL 1553502",
      "LAW_CAT_CD": "F",
      "ARREST_BORO": "M",
      "ARREST_PRECINCT": "5",
      "JURISDICTION_CODE": 0,
      "AGE_GROUP": "<18",
      "PERP_SEX": "M",
      "PERP_RACE": "BLACK",
      "X_COORD_CD": "983907",
      "Y_COORD_CD": 199959.0,
      "Latitude": 40.71552621300003,
      "Longitude": -74.00123874799993,
      "Lon_Lat": "POINT (-74.00123874799993 40.71552621300003)"
    },
    {
      "ARREST_KEY": 194591136,
      "ARREST_DATE": "2019-03-12 00:00:00",
      "PD_CD": 157,
      "PD_DESC": "RAPE 1",
      "KY_CD": "104",
      "OFNS_DESC": "RAPE",
      "LAW_CODE": "PL 1303501",
      "LAW_CAT_CD": "F",
      "ARREST_BORO": "K",
      "ARREST_PRECINCT": "77",
      "JURISDICTION_CODE": 0,
      "AGE_GROUP": "25-44",
      "PERP_SEX": "M",
      "PERP_RACE": "BLACK",
      "X_COORD_CD": "1003606",
      "Y_COORD_CD": 185050.0,
      "Latitude": 40.67458330800008,
      "Longitude": -73.93022154099998,
      "Lon_Lat": "POINT (-73.93022154099998 40.67458330800008)"
    },
    {
      "ARREST_KEY": 234348034,
      "ARREST_DATE": "2021-10-01 00:00:00",
      "PD_CD": 153,
      "PD_DESC": "RAPE 3",
      "KY_CD": "104",
      "OFNS_DESC": "RAPE",
      "LAW_CODE": "PL 1302501",
      "LAW_CAT_CD": "F",
      "ARREST_BORO": "M",
      "ARREST_PRECINCT": "5",
      "JURISDICTION_CODE": 0,
      "AGE_GROUP": "<18",
      "PERP_SEX": "M",
      "PERP_RACE": "BLACK",
      "X_COORD_CD": "984946",
      "Y_COORD_CD": 200203.0,
      "Latitude": 40.716195914000025,
      "Longitude": -73.99749074599998,
      "Lon_Lat": "POINT (-73.99749074599998 40.716195914000025)"
    },
    {
      "ARREST_KEY": 191778810,
      "ARREST_DATE": "2019-01-02 00:00:00",
      "PD_CD": 168,
      "PD_DESC": "SODOMY 1",
      "KY_CD": "116",
      "OFNS_DESC": "SEX CRIMES",
      "LAW_CODE": "PL 1305003",
      "LAW_CAT_CD": "F",
      "ARREST_BORO": "Q",
      "ARREST_PRECINCT": "112",
      "JURISDICTION_CODE": 0,
      "AGE_GROUP": "<18",
      "PERP_SEX": "M",
      "PERP_RACE": "WHITE",
      "X_COORD_CD": "1025420",
      "Y_COORD_CD": 202485.0,
      "Latitude": 40.72236368700004,
      "Longitude": -73.85147389399998,
      "Lon_Lat": "POINT (-73.85147389399998 40.72236368700005)"
    },
    {
      "ARREST_KEY": 218265913,
      "ARREST_DATE": "2020-09-24 00:00:00",
      "PD_CD": 153,
      "PD_DESC": "RAPE 3",
      "KY_CD": "104",
      "OFNS_DESC": "RAPE",
      "LAW_CODE": "PL 1302503",
      "LAW_CAT_CD": "F",
      "ARREST_BORO": "B",
      "ARREST_PRECINCT": "40",
      "JURISDICTION_CODE": 2,
      "AGE_GROUP": "18-24",
      "PERP_SEX": "M",
      "PERP_RACE": "WHITE HISPANIC",
      "X_COORD_CD": "1004926",
      "Y_COORD_CD": 234532.0,
      "Latitude": 40.81039601900005,
      "Longitude": -73.92531074499993,
      "Lon_Lat": "POINT (-73.92531074499993 40.81039601900005)"
    },
    {
      "ARREST_KEY": 235277304,
      "ARREST_DATE": "2021-10-21 00:00:00",
      "PD_CD": 157,
      "PD_DESC": "RAPE 1",
      "KY_CD": "104",
      "OFNS_DESC": "RAPE",
      "LAW_CODE": "PL 1303501",
      "LAW_CAT_CD": "F",
      "ARREST_BORO": "M",
      "ARREST_PRECINCT": "30",
      "JURISDICTION_CODE": 0,
      "AGE_GROUP": "45-64",
      "PERP_SEX": "M",
      "PERP_RACE": "BLACK",
      "X_COORD_CD": "999794",
      "Y_COORD_CD": 241252.0,
      "Latitude": 40.82885104500008,
      "Longitude": -73.94383419099995,
      "Lon_Lat": "POINT (-73.94383419099995 40.82885104500008)"
    },
    {
      "ARREST_KEY": 234945567,
      "ARREST_DATE": "2021-10-14 00:00:00",
      "PD_CD": 153,
      "PD_DESC": "RAPE 3",
      "KY_CD": "104",
      "OFNS_DESC": "RAPE",
      "LAW_CODE": "PL 1302502",
      "LAW_CAT_CD": "F",
      "ARREST_BORO": "K",
      "ARREST_PRECINCT": "77",
      "JURISDICTION_CODE": 0,
      "AGE_GROUP": "25-44",
      "PERP_SEX": "M",
      "PERP_RACE": "BLACK",
      "X_COORD_CD": "1003606",
      "Y_COORD_CD": 185050.0,
      "Latitude": 40.67458330800008,
      "Longitude": -73.93022154099998,
      "Lon_Lat": "POINT (-73.93022154099998 40.67458330800008)"
    },
    {
      "ARREST_KEY": 217780931,
      "ARREST_DATE": "2020-09-14 00:00:00",
      "PD_CD": 105,
      "PD_DESC": "STRANGULATION 1ST",
      "KY_CD": "106",
      "OFNS_DESC": "FELONY ASSAULT",
      "LAW_CODE": "PL 1211200",
      "LAW_CAT_CD": "F",
      "ARREST_BORO": "M",
      "ARREST_PRECINCT": "10",
      "JURISDICTION_CODE": 0,
      "AGE_GROUP": "25-44",
      "PERP_SEX": "M",
      "PERP_RACE": "BLACK",
      "X_COORD_CD": "985783",
      "Y_COORD_CD": 214675.0,
      "Latitude": 40.755917883000045,
      "Longitude": -73.99446811699994,
      "Lon_Lat": "POINT (-73.99446811699994 40.755917883000045)"
    },
    {
      "ARREST_KEY": 234846393,
      "ARREST_DATE": "2021-10-12 00:00:00",
      "PD_CD": 153,
      "PD_DESC": "RAPE 3",
      "KY_CD": "104",
      "OFNS_DESC": "RAPE",
      "LAW_CODE": "PL 1302501",
      "LAW_CAT_CD": "F",
      "ARREST_BORO": "Q",
      "ARREST_PRECINCT": "112",
      "JURISDICTION_CODE": 0,
      "AGE_GROUP": "45-64",
      "PERP_SEX": "M",
      "PERP_RACE": "BLACK",
      "X_COORD_CD": "1025420",
      "Y_COORD_CD": 202485.0,
      "Latitude": 40.72236368700004,
      "Longitude": -73.85147389399998,
      "Lon_Lat": "POINT (-73.85147389399998 40.72236368700004)"
    },
    {
      "ARREST_KEY": 219591640,
      "ARREST_DATE": "2020-10-22 00:00:00",
      "PD_CD": 155,
      "PD_DESC": "RAPE 2",
      "KY_CD": "104",
      "OFNS_DESC": "RAPE",
      "LAW_CODE": "PL 1303001",
      "LAW_CAT_CD": "F",
      "ARREST_BORO": "K",
      "ARREST_PRECINCT": "77",
      "JURISDICTION_CODE": 0,
      "AGE_GROUP": "25-44",
      "PERP_SEX": "M",
      "PERP_RACE": "WHITE HISPANIC",
      "X_COORD_CD": "1003606",
      "Y_COORD_CD": 185050.0,
      "Latitude": 40.67458330800008,
      "Longitude": -73.93022154099998,
      "Lon_Lat": "POINT (-73.93022154099998 40.67458330800008)"
    },
    {
      "ARREST_KEY": 187603736,
      "ARREST_DATE": "2018-09-14 00:00:00",
      "PD_CD": 157,
      "PD_DESC": "RAPE 1",
      "KY_CD": "104",
      "OFNS_DESC": "RAPE",
      "LAW_CODE": "PL 1303501",
      "LAW_CAT_CD": "F",
      "ARREST_BORO": "B",
      "ARREST_PRECINCT": "48",
      "JURISDICTION_CODE": 0,
      "AGE_GROUP": "25-44",
      "PERP_SEX": "M",
      "PERP_RACE": "WHITE HISPANIC",
      "X_COORD_CD": "1011779",
      "Y_COORD_CD": 246746.0,
      "Latitude": 40.84390125500005,
      "Longitude": -73.900504632,
      "Lon_Lat": "POINT (-73.900504632 40.843901255000056)"
    },
    {
      "ARREST_KEY": 188126065,
      "ARREST_DATE": "2018-09-28 00:00:00",
      "PD_CD": null,
      "PD_DESC": null,
      "KY_CD": null,
      "OFNS_DESC": null,
      "LAW_CODE": "PL 1701000",
      "LAW_CAT_CD": "F",
      "ARREST_BORO": "M",
      "ARREST_PRECINCT": "23",
      "JURISDICTION_CODE": 1,
      "AGE_GROUP": "25-44",
      "PERP_SEX": "M",
      "PERP_RACE": "WHITE HISPANIC",
      "X_COORD_CD": "998736",
      "Y_COORD_CD": 227214.0,
      "Latitude": 40.79032242500005,
      "Longitude": -73.94768749799994,
      "Lon_Lat": "POINT (-73.94768749799994 40.79032242500005)"
    },
    {
      "ARREST_KEY": 235215296,
      "ARREST_DATE": "2021-10-20 00:00:00",
      "PD_CD": 155,
      "PD_DESC": "RAPE 2",
      "KY_CD": "104",
      "OFNS_DESC": "RAPE",
      "LAW_CODE": "PL 1303001",
      "LAW_CAT_CD": "F",
      "ARREST_BORO": "B",
      "ARREST_PRECINCT": "41",
      "JURISDICTION_CODE": 0,
      "AGE_GROUP": "45-64",
      "PERP_SEX": "M",
      "PERP_RACE": "BLACK",
      "X_COORD_CD": "1013232",
      "Y_COORD_CD": 236725.0,
      "Latitude": 40.816391847000034,
      "Longitude": -73.89529641399997,
      "Lon_Lat": "POINT (-73.89529641399997 40.816391847000034)"
    },
    {
      "ARREST_KEY": 235213642,
      "ARREST_DATE": "2021-10-20 00:00:00",
      "PD_CD": 157,
      "PD_DESC": "RAPE 1",
      "KY_CD": "104",
      "OFNS_DESC": "RAPE",
      "LAW_CODE": "PL 1303501",
      "LAW_CAT_CD": "F",
      "ARREST_BORO": "Q",
      "ARREST_PRECINCT": "112",
      "JURISDICTION_CODE": 0,
      "AGE_GROUP": "18-24",
      "PERP_SEX": "M",
      "PERP_RACE": "WHITE HISPANIC",
      "X_COORD_CD": "1025420",
      "Y_COORD_CD": 202485.0,
      "Latitude": 40.72236368700004,
      "Longitude": -73.85147389399998,
      "Lon_Lat": "POINT (-73.85147389399998 40.72236368700004)"
    },
    {
      "ARREST_KEY": 188593338,
      "ARREST_DATE": "2018-10-10 00:00:00",
      "PD_CD": 177,
      "PD_DESC": null,
      "KY_CD": null,
      "OFNS_DESC": null,
      "LAW_CODE": "PL 1306504",
      "LAW_CAT_CD": "F",
      "ARREST_BORO": "M",
      "ARREST_PRECINCT": "25",
      "JURISDICTION_CODE": 0,
      "AGE_GROUP": "45-64",
      "PERP_SEX": "M",
      "PERP_RACE": "BLACK",
      "X_COORD_CD": "1000555",
      "Y_COORD_CD": 230994.0,
      "Latitude": 40.800694331000045,
      "Longitude": -73.94110928599997,
      "Lon_Lat": "POINT (-73.94110928599997 40.800694331000045)"
    },
    {
      "ARREST_KEY": 188785833,
      "ARREST_DATE": "2018-10-15 00:00:00",
      "PD_CD": null,
      "PD_DESC": null,
      "KY_CD": null,
      "OFNS_DESC": null,
      "LAW_CODE": null,
      "LAW_CAT_CD": null,
      "ARREST_BORO": "K",
      "ARREST_PRECINCT": "67",
      "JURISDICTION_CODE": 0,
      "AGE_GROUP": "25-44",
      "PERP_SEX": "M",
      "PERP_RACE": "BLACK",
      "X_COORD_CD": "996949",
      "Y_COORD_CD": 176623.0,
      "Latitude": 40.651465108000025,
      "Longitude": -73.95423641599997,
      "Lon_Lat": "POINT (-73.95423641599997 40.651465108000025)"
    },
    {
      "ARREST_KEY": 235916883,
      "ARREST_DATE": "2021-11-05 00:00:00",
      "PD_CD": 153,
      "PD_DESC": "RAPE 3",
      "KY_CD": "104",
      "OFNS_DESC": "RAPE",
      "LAW_CODE": "PL 1302502",
      "LAW_CAT_CD": "F",
      "ARREST_BORO": "B",
      "ARREST_PRECINCT": "48",
      "JURISDICTION_CODE": 0,
      "AGE_GROUP": "25-44",
      "PERP_SEX": "M",
      "PERP_RACE": "WHITE HISPANIC",
      "X_COORD_CD": "1011779",
      "Y_COORD_CD": 246746.0,
      "Latitude": 40.84390125500005,
      "Longitude": -73.900504632,
      "Lon_Lat": "POINT (-73.900504632 40.84390125500005)"
    }
  ]
}